LICENSE
README.md
redalert/__init__.py
redalert/_version.py
redalert/main.py
containment_chamber-0.1.0.dist-info/METADATA
containment_chamber-0.1.0.dist-info/WHEEL
containment_chamber-0.1.0.dist-info/entry_points.txt
containment_chamber-0.1.0.dist-info/licenses/LICENSE
containment_chamber-0.1.0.dist-info/RECORD
