Metadata-Version: 2.4
Name: containment-chamber
Version: 0.1.0
Summary: A tool for containment chamber functionality
Project-URL: Homepage, https://github.com/Mockapapella/containment-chamber
Project-URL: Repository, https://github.com/Mockapapella/containment-chamber
Project-URL: Issues, https://github.com/Mockapapella/containment-chamber/issues
Author: Mockapapella
License: MIT
License-File: LICENSE
Classifier: Intended Audience :: Developers
Classifier: License :: OSI Approved :: MIT License
Classifier: Programming Language :: Python :: 3
Classifier: Programming Language :: Python :: 3.9
Classifier: Programming Language :: Python :: 3.10
Classifier: Programming Language :: Python :: 3.11
Classifier: Programming Language :: Python :: 3.12
Classifier: Programming Language :: Python :: 3.13
Requires-Python: >=3.9
